casefoam/__init__.py
casefoam/core.py
casefoam/loadData.py
casefoam/mkCases.py
casefoam/postFunctions.py
casefoam/utility.py
casefoam-0.2.0.data/scripts/foamState
casefoam-0.2.0.dist-info/LICENSE
casefoam-0.2.0.dist-info/METADATA
casefoam-0.2.0.dist-info/WHEEL
casefoam-0.2.0.dist-info/top_level.txt
casefoam-0.2.0.dist-info/RECORD
