Metadata-Version: 2.1
Name: casefoam
Version: 0.2.0
Summary: Create and manipulate OpenFOAM cases
Home-page: https://github.com/DLR-RY/caseFoam
Author: Joe Pearson and Henning Scheufler
Author-email: Henning.Scheufler@dlr.de
License: GPLv3
Project-URL: Documentation, https://casefoam.readthedocs.io/en/latest/
Project-URL: Issue Tracker, https://github.com/DLR-RY/caseFoam/issues
Keywords: cfd,openfoam,postProcessing,automation
Platform: UNKNOWN
Classifier: Development Status :: 5 - Production/Stable
Classifier: Intended Audience :: Science/Research
Classifier: License :: OSI Approved :: GNU General Public License v3 or later (GPLv3+)
Classifier: Operating System :: Unix
Classifier: Operating System :: POSIX
Classifier: Operating System :: Microsoft :: Windows
Classifier: Programming Language :: Python
Classifier: Programming Language :: Python :: 3
Classifier: Programming Language :: Python :: 3 :: Only
Classifier: Programming Language :: Python :: 3.6
Classifier: Programming Language :: Python :: 3.7
Classifier: Programming Language :: Python :: 3.8
Classifier: Programming Language :: Python :: 3.9
Classifier: Programming Language :: Python :: 3.10
Classifier: Topic :: Utilities
Classifier: Topic :: Scientific/Engineering
Requires-Python: >=3.6
License-File: LICENSE
Requires-Dist: pyfoam (>=0.6.7)
Requires-Dist: pandas (>=0.23.0)
Provides-Extra: dev
Requires-Dist: pytest (>=6.2.3) ; extra == 'dev'
Requires-Dist: sphinx-rtd-theme ; extra == 'dev'
Requires-Dist: numpydoc ; extra == 'dev'
Requires-Dist: sphinx ; extra == 'dev'
Requires-Dist: ipython ; extra == 'dev'
Provides-Extra: plot
Requires-Dist: seaborn (>=0.8) ; extra == 'plot'
